ontobio/__init__.py
ontobio/assoc_factory.py
ontobio/assoc_schema.py
ontobio/assocmodel.py
ontobio/cgraph.py
ontobio/config.py
ontobio/config.yaml
ontobio/ecomap.py
ontobio/lexmap.py
ontobio/obograph_util.py
ontobio/ontol.py
ontobio/ontol_factory.py
ontobio/slimmer.py
ontobio/tsv_expander.py
ontobio/xref_util.py
ontobio/analysis/__init__.py
ontobio/analysis/semsim.py
ontobio/golr/__init__.py
ontobio/golr/beacon_query.py
ontobio/golr/golr_associations.py
ontobio/golr/golr_entities.py
ontobio/golr/golr_matrix.py
ontobio/golr/golr_query.py
ontobio/golr/golr_sim.py
ontobio/golr/golr_stats.py
ontobio/io/__init__.py
ontobio/io/assocparser.py
ontobio/io/assocwriter.py
ontobio/io/differ.py
ontobio/io/entityparser.py
ontobio/io/entitywriter.py
ontobio/io/gaference.py
ontobio/io/gafgpibridge.py
ontobio/io/gafparser.py
ontobio/io/gpadparser.py
ontobio/io/hpoaparser.py
ontobio/io/ontol_renderers.py
ontobio/io/parsereport.py
ontobio/io/qc.py
ontobio/model/GolrResults.py
ontobio/model/OBOGraph.py
ontobio/model/__init__.py
ontobio/model/association.py
ontobio/model/bbop_graph.py
ontobio/model/biomodel.py
ontobio/model/collections.py
ontobio/model/nlp.py
ontobio/model/similarity.py
ontobio/model/mme/__init__.py
ontobio/model/mme/request.py
ontobio/model/mme/response.py
ontobio/neo/__init__.py
ontobio/neo/scigraph_ontology.py
ontobio/rdfgen/__init__.py
ontobio/rdfgen/assoc_rdfgen.py
ontobio/rdfgen/relations.py
ontobio/rdfgen/gocamgen/__init__.py
ontobio/rdfgen/gocamgen/collapsed_assoc.py
ontobio/rdfgen/gocamgen/errors.py
ontobio/rdfgen/gocamgen/filter_rule.py
ontobio/rdfgen/gocamgen/gocam_builder.py
ontobio/rdfgen/gocamgen/gocamgen.py
ontobio/rdfgen/gocamgen/rdflib_sparql_wrapper.py
ontobio/rdfgen/gocamgen/subgraphs.py
ontobio/rdfgen/gocamgen/triple_pattern_finder.py
ontobio/rdfgen/gocamgen/utils.py
ontobio/sim/__init__.py
ontobio/sim/annotation_scorer.py
ontobio/sim/mme.py
ontobio/sim/phenosim_engine.py
ontobio/sim/sim_engine.py
ontobio/sim/api/__init__.py
ontobio-2.9.12.dist-info/LICENSE
ontobio-2.9.12.dist-info/METADATA
ontobio-2.9.12.dist-info/WHEEL
ontobio-2.9.12.dist-info/top_level.txt
ontobio-2.9.12.dist-info/RECORD
