Metadata-Version: 2.1
Name: ontobio
Version: 2.9.12
Summary: Library for working with OBO Library Ontologies and associations
Home-page: https://github.com/biolink/ontobio
Author: Chris Mungall
Author-email: cmungall@gmail.com
License: BSD
Keywords: ontology graph obo owl sparql networkx network
Platform: UNKNOWN
Classifier: Intended Audience :: Science/Research
Classifier: Topic :: Scientific/Engineering :: Bio-Informatics
Classifier: Topic :: Scientific/Engineering :: Information Analysis
Classifier: License :: OSI Approved :: BSD License
Classifier: Programming Language :: Python :: 3
Classifier: Topic :: Scientific/Engineering :: Visualization
License-File: LICENSE
Requires-Dist: rdflib>=6.0.0
Requires-Dist: marshmallow<4.0,>=3.0.0b11
Requires-Dist: jsobject>=0.0
Requires-Dist: prefixcommons>=0.1.9
Requires-Dist: requests>=0.0
Requires-Dist: pip>=9.0.1
Requires-Dist: wheel>0.25.0
Requires-Dist: pysolr>=3.6.0
Requires-Dist: networkx>=2.3
Requires-Dist: matplotlib>=2.0.0
Requires-Dist: SPARQLWrapper>=1.8.0
Requires-Dist: pandas>=0.0
Requires-Dist: scipy>=1.2.0
Requires-Dist: twine
Requires-Dist: jsonpickle>=0.0
Requires-Dist: jsonpath-rw>=0.0
Requires-Dist: PyShEx>=0.7.11
Requires-Dist: pytest>=0.0
Requires-Dist: pytest-logging>=0.0
Requires-Dist: pydotplus>=0.0
Requires-Dist: plotly>=2.0.7
Requires-Dist: pyyaml
Requires-Dist: yamldown>=0.1.7
Requires-Dist: click
Requires-Dist: diskcache>=4.0.0
Requires-Dist: bidict>=0.20.0
Requires-Dist: python-dateutil
Requires-Dist: chardet
Requires-Dist: dacite>=1.6.0
Requires-Dist: pyparsing==2.4.7
Provides-Extra: dev
Requires-Dist: plotly; extra == "dev"
Provides-Extra: test
Requires-Dist: pytest; extra == "test"
